{
  "serial_port": "/dev/ttyS1",
  "baud_rate": 57600,
  "web_port": 3000,
  "web_host": "0.0.0.0",
  "telemetry_rate": 100,
  "heartbeat_interval": 1,
  "bridge_host": "127.0.0.1",
  "bridge_command_port": 14551,
  "bridge_telemetry_port": 14552,
  "wireless_interface": "p2p0",
  "can_interface": "can0",
  "manta_host": "10.42.0.1",
  "rover_throttle_min": -100,
  "rover_throttle_max": 100,
  "rover_steering_min": -45,
  "rover_steering_max": 45,
  "rover_left_channel": 1,
  "rover_right_channel": 3,
  "rover_steering_input_channel": 1,
  "rover_throttle_input_channel": 3,
  "logs_dir": "./logs",
  "enable_https": false,
  "ssl_cert": "",
  "ssl_key": "",
  "max_motor_pwm": 2000,
  "min_motor_pwm": 1000,
  "default_motor_pwm": 1500,
  "motor_channels": 8,
  "auto_start_mavlink": true,
  "debug_mode": true,
  "hotspot": {
    "enabled": true,
    "connection_name": "Manta-Control-Hotspot",
    "ssid": "Manta-Control",
    "password": "manta",
    "interface": "p2p0",
    "fallback_interface": "wlan0",
    "band": "bg",
    "channel": 6,
    "portal_ip": "10.42.0.1",
    "portal_port": 80,
    "camera_port": 8090
  },
  "camera": {
    "enabled": true,
    "label": "OV8858 Camera",
    "transport": "local",
    "sensor": "ov8858",
    "port": "cam2",
    "boot_config": "/boot/firmware/ubuntuEnv.txt",
    "overlay": "rk3588-lubancat-5-cam2-ov8858-1632x1224-30fps-overlay",
    "device": "auto",
    "width": 1632,
    "height": 1224,
    "fps": 30,
    "refresh_ms": 80,
    "stall_reconnect_seconds": 3.0,
    "sensor_controls": {
      "exposure": 1500,
      "analogue_gain": 200
    },
    "snapshot_filter": "",
    "sensor_control_reapply_seconds": [1.5, 4.0],
    "source_type": "mjpeg",
    "local_source_url": "http://127.0.0.1:8090/snapshot.jpg",
    "local_stream_url": "http://127.0.0.1:8090/stream.mjpg",
    "source_url": "/api/camera/stream",
    "open_url": "/api/camera/stream"
  },
  "vision": {
    "snapshot_url": "http://127.0.0.1:8090/snapshot.jpg",
    "rover_api": "http://127.0.0.1:3000/api/control/rover",
    "max_steering": 27.0,
    "track_min_forward_pwm": 80,
    "loop_hz": 5.0,
    "detect_width": 640,
    "conf_threshold": 0.2,
    "iou_threshold": 0.45,
    "lost_seconds": 1.0
  }
}
